[{"id":"user-image-Untitled-1-min.png","publicUrl":"np://user.desktop.nicepage.com/Site_1592210559/images/Untitled-1-min.png","size":163916,"hash":"Y27Wn1i4tkD4D8pgSSoRLSqAxDQ=","fileName":"Untitled-1-min.png","name":"Untitled-1-min","width":848,"height":681,"thumbnail":{"url":"np://user.desktop.nicepage.com/Site_1592210559/images/thumbnails/Untitled-1-min.png","width":250,"height":201},"folderId":null,"originalUrl":"//images01.nicepagecdn.com/c461c07a441a5d220e8feb1a/64ed3ea98a28516e97684d88/Untitled-1-min.png","usages":[]},{"id":"user-image-tesla-9.svg","publicUrl":"np://user.desktop.nicepage.com/Site_1592210559/images/tesla-9.svg","size":1198,"hash":"11Dz0VDc42XRaIKKOJVzlf2R+9M=","fileName":"tesla-9.svg","name":"tesla-9","width":2500,"height":326,"thumbnail":{"url":"np://user.desktop.nicepage.com/Site_1592210559/images/thumbnails/tesla-9.svg","width":250,"height":33},"folderId":null,"originalUrl":"//images01.nicepagecdn.com/c461c07a441a5d220e8feb1a/75b9a80337b65bc28863c8aa/tesla-9.svg","usages":[]},{"id":"user-image-sony-logo.svg","publicUrl":"np://user.desktop.nicepage.com/Site_1592210559/images/sony-logo.svg","size":2693,"hash":"QpbCOeE7tQC5BOPp5Klk+K7KVkQ=","fileName":"sony-logo.svg","name":"sony-logo","width":2500,"height":448,"thumbnail":{"url":"np://user.desktop.nicepage.com/Site_1592210559/images/thumbnails/sony-logo.svg","width":250,"height":45},"folderId":null,"originalUrl":"//images01.nicepagecdn.com/c461c07a441a5d220e8feb1a/619f5d548d635e75bcf2f320/sony-logo.svg","usages":[]},{"id":"user-image-evga.svg","publicUrl":"np://user.desktop.nicepage.com/Site_1592210559/images/evga.svg","size":2699,"hash":"lOzuRGUOeAuo5UBSLlm99TS0/+0=","fileName":"evga.svg","name":"evga","width":2500,"height":523,"thumbnail":{"url":"np://user.desktop.nicepage.com/Site_1592210559/images/thumbnails/evga.svg","width":250,"height":52},"folderId":null,"originalUrl":"//images01.nicepagecdn.com/c461c07a441a5d220e8feb1a/a33a46c929de5630ba07635e/evga.svg","usages":[]},{"id":"user-image-logo-amazon.svg","publicUrl":"np://user.desktop.nicepage.com/Site_1592210559/images/logo-amazon.svg","size":5016,"hash":"+m2eS2RvVL6Q/p0RrDoZIg0E6hM=","fileName":"logo-amazon.svg","name":"logo-amazon","width":2500,"height":752,"thumbnail":{"url":"np://user.desktop.nicepage.com/Site_1592210559/images/thumbnails/logo-amazon.svg","width":250,"height":75},"folderId":null,"originalUrl":"//images01.nicepagecdn.com/c461c07a441a5d220e8feb1a/8164ad3ec7d75a9a81a12288/logo-amazon.svg","usages":[]},{"id":"user-image-1.svg","publicUrl":"np://user.desktop.nicepage.com/Site_1592210559/images/1.svg","size":6343,"hash":"tYV+Qo4ZKryfT9mENdnWEd9ph2M=","fileName":"1.svg","name":"1","width":2500,"height":752,"thumbnail":{"url":"np://user.desktop.nicepage.com/Site_1592210559/images/thumbnails/1.svg","width":250,"height":75},"folderId":null,"originalUrl":"//images01.nicepagecdn.com/c461c07a441a5d220e8feb1a/5ec8b52fcf09516295c018eb/1.svg","usages":[]},{"id":"user-image-54645.jpg","publicUrl":"np://user.desktop.nicepage.com/Site_1592210559/images/54645.jpg","size":31381,"hash":"HrlZ+2FARpCfTS+GvCsfIDTUQMQ=","fileName":"54645.jpg","name":"54645","width":404,"height":404,"thumbnail":{"url":"np://user.desktop.nicepage.com/Site_1592210559/images/thumbnails/54645.jpg","width":250,"height":250},"folderId":null,"originalUrl":"https://assets.nicepagecdn.com/d2cc3eaa/460597/images/54645.jpg","usages":["414225160"]},{"id":"user-image-6.jpg","publicUrl":"np://user.desktop.nicepage.com/Site_1592210559/images/6.jpg","size":33451,"hash":"CThoEK/2TAbCydL2qQr5ih3CLEQ=","fileName":"6.jpg","name":"6","width":404,"height":404,"thumbnail":{"url":"np://user.desktop.nicepage.com/Site_1592210559/images/thumbnails/6.jpg","width":250,"height":250},"folderId":null,"originalUrl":"https://assets.nicepagecdn.com/d2cc3eaa/460597/images/6.jpg","usages":[]},{"id":"user-image-345325.jpg","publicUrl":"np://user.desktop.nicepage.com/Site_1592210559/images/345325.jpg","size":24689,"hash":"MFDBmADt2z5AsQGx0QShWdpaOR4=","fileName":"345325.jpg","name":"345325","width":404,"height":404,"thumbnail":{"url":"np://user.desktop.nicepage.com/Site_1592210559/images/thumbnails/345325.jpg","width":250,"height":250},"folderId":null,"originalUrl":"https://assets.nicepagecdn.com/d2cc3eaa/460597/images/345325.jpg","usages":[]},{"id":"user-image-fggf.jpg","publicUrl":"np://user.desktop.nicepage.com/Site_1592210559/images/fggf.jpg","size":29555,"hash":"Kj7SsWxeOq6xR4/4zIDY8gk5yEk=","fileName":"fggf.jpg","name":"fggf","width":404,"height":404,"thumbnail":{"url":"np://user.desktop.nicepage.com/Site_1592210559/images/thumbnails/fggf.jpg","width":250,"height":250},"folderId":null,"originalUrl":"//images01.nicepagecdn.com/c461c07a441a5d220e8feb1a/47d488474b1750ad8f9a684f/fggf.jpg","usages":["414225160"]},{"id":"user-image-fff.jpg","publicUrl":"np://user.desktop.nicepage.com/Site_1592210559/images/fff.jpg","size":25904,"hash":"fMm7Rd0l+7sWotkw331HG67oZUM=","fileName":"fff.jpg","name":"fff","width":404,"height":404,"thumbnail":{"url":"np://user.desktop.nicepage.com/Site_1592210559/images/thumbnails/fff.jpg","width":250,"height":250},"folderId":null,"originalUrl":"//images01.nicepagecdn.com/c461c07a441a5d220e8feb1a/dee2a7ea9eea577cab16110a/fff.jpg","usages":[]},{"id":"user-image-2.jpg","publicUrl":"np://user.desktop.nicepage.com/Site_1592210559/images/2.jpg","size":24248,"hash":"mvndyatakqMP7TBAj9rWTL7lVWw=","fileName":"2.jpg","name":"2","width":404,"height":404,"thumbnail":{"url":"np://user.desktop.nicepage.com/Site_1592210559/images/thumbnails/2.jpg","width":250,"height":250},"folderId":null,"originalUrl":"//images01.nicepagecdn.com/c461c07a441a5d220e8feb1a/23f2b6ec8f435911852884f1/2.jpg","usages":[]},{"id":"user-image-120827.png","publicUrl":"np://user.desktop.nicepage.com/Site_1592210559/images/120827.png","size":375,"hash":"dLdb74LISNvDrqnKjx3+RPhgiBk=","fileName":"120827.png","name":"120827","width":128,"height":128,"thumbnail":{"url":"np://user.desktop.nicepage.com/Site_1592210559/images/thumbnails/120827.png","width":128,"height":128,"length":375,"type":"png"},"folderId":null,"originalUrl":"https://assets.nicepagecdn.com/11a8ddce/6486286/images/120827.png","usages":[]},{"id":"user-image-6604870.png","publicUrl":"np://user.desktop.nicepage.com/Site_1592210559/images/6604870.png","size":1410,"hash":"JgATw1lIiAQYKlmJ9KFnOleaXTM=","fileName":"6604870.png","name":"6604870","width":128,"height":128,"thumbnail":{"url":"np://user.desktop.nicepage.com/Site_1592210559/images/thumbnails/6604870.png","width":128,"height":128,"length":1410,"type":"png"},"folderId":null,"originalUrl":"https://assets.nicepagecdn.com/11a8ddce/6471648/images/6604870.png","usages":[]},{"id":"user-image-2148859448.jpg","publicUrl":"np://user.desktop.nicepage.com/Site_1592210559/images/2148859448.jpg","size":1522385,"hash":"uCIufeuECCMpsy5d9N8mRI1+q+E=","fileName":"2148859448.jpg","name":"2148859448","width":1500,"height":1500,"thumbnail":{"url":"np://user.desktop.nicepage.com/Site_1592210559/images/thumbnails/2148859448.jpg","width":250,"height":250},"folderId":null,"originalUrl":"https://assets.nicepagecdn.com/11a8ddce/6471648/images/2148859448.jpg","usages":[]},{"id":"user-image-137722.jpg","publicUrl":"np://user.desktop.nicepage.com/Site_1592210559/images/137722.jpg","size":822391,"hash":"9eJ/KOdlLQVToOQb48pfB4+fMQY=","fileName":"137722.jpg","name":"137722","width":1920,"height":1920,"thumbnail":{"url":"np://user.desktop.nicepage.com/Site_1592210559/images/thumbnails/137722.jpg","width":250,"height":250},"folderId":null,"originalUrl":"https://assets.nicepagecdn.com/11a8ddce/6471648/images/137722.jpg","usages":[]},{"id":"user-image-16993.jpg","publicUrl":"np://user.desktop.nicepage.com/Site_1592210559/images/16993.jpg","size":1901921,"hash":"r1JTvWUepg7YLUbel9etonXWY8k=","fileName":"16993.jpg","name":"16993","width":2000,"height":1333,"thumbnail":{"url":"np://user.desktop.nicepage.com/Site_1592210559/images/thumbnails/16993.jpg","width":250,"height":167},"folderId":null,"originalUrl":"https://assets.nicepagecdn.com/11a8ddce/6486286/images/16993.jpg","usages":[]},{"id":"user-image-14595.jpg","publicUrl":"np://user.desktop.nicepage.com/Site_1592210559/images/14595.jpg","size":899759,"hash":"DnGQ3+z3XBXtw/82iBTM6TTOKjA=","fileName":"14595.jpg","name":"14595","width":2000,"height":1333,"thumbnail":{"url":"np://user.desktop.nicepage.com/Site_1592210559/images/thumbnails/14595.jpg","width":250,"height":167},"folderId":null,"originalUrl":"https://assets.nicepagecdn.com/11a8ddce/6486286/images/14595.jpg","usages":[]},{"id":"user-image-2149051726.jpg","publicUrl":"np://user.desktop.nicepage.com/Site_1592210559/images/2149051726.jpg","size":698665,"hash":"L7nYqRpy1Oq/gNwsb5/fQhQ3+mo=","fileName":"2149051726.jpg","name":"2149051726","width":1000,"height":1500,"thumbnail":{"url":"np://user.desktop.nicepage.com/Site_1592210559/images/thumbnails/2149051726.jpg","width":167,"height":250},"folderId":null,"originalUrl":"https://assets.nicepagecdn.com/11a8ddce/6486286/images/2149051726.jpg","usages":[]},{"id":"user-image-20967.jpg","publicUrl":"np://user.desktop.nicepage.com/Site_1592210559/images/20967.jpg","size":3833131,"hash":"qZw/lsoiei8AV5n9LPxfyE1Svxk=","fileName":"20967.jpg","name":"20967","width":2000,"height":1459,"thumbnail":{"url":"np://user.desktop.nicepage.com/Site_1592210559/images/thumbnails/20967.jpg","width":250,"height":182},"folderId":null,"originalUrl":"https://assets.nicepagecdn.com/11a8ddce/6486286/images/20967.jpg","usages":[]},{"id":"user-image-6180.jpg","publicUrl":"np://user.desktop.nicepage.com/Site_1592210559/images/6180.jpg","size":1833113,"hash":"zBCSNrwXB/0Zsd0GVKpmYZ2W6DE=","fileName":"6180.jpg","name":"6180","width":1334,"height":2000,"thumbnail":{"url":"np://user.desktop.nicepage.com/Site_1592210559/images/thumbnails/6180.jpg","width":167,"height":250},"folderId":null,"originalUrl":"https://assets.nicepagecdn.com/11a8ddce/6486286/images/6180.jpg","usages":[]},{"id":"user-image-10897.jpg","publicUrl":"np://user.desktop.nicepage.com/Site_1592210559/images/10897.jpg","size":573712,"hash":"geS6u1lIL4ZktU5Jhb8OXLcDIOQ=","fileName":"10897.jpg","name":"10897","width":1000,"height":1500,"thumbnail":{"url":"np://user.desktop.nicepage.com/Site_1592210559/images/thumbnails/10897.jpg","width":167,"height":250},"folderId":null,"originalUrl":"https://assets.nicepagecdn.com/11a8ddce/6486286/images/10897.jpg","usages":[]},{"id":"user-image-Untitled2.jpg","publicUrl":"np://user.desktop.nicepage.com/Site_1592210559/images/Untitled2.jpg","size":581342,"hash":"es9DW5khcmLeIrku4D2Nb22ZKtE=","fileName":"Untitled2.jpg","name":"Untitled2","width":1500,"height":1125,"thumbnail":{"url":"np://user.desktop.nicepage.com/Site_1592210559/images/thumbnails/Untitled2.jpg","width":250,"height":188},"folderId":null,"originalUrl":"//images03.nicepage.com/a1389d7bc73adea1e1c1fb7e/c7ab9ce6860457d79f62cff9/Untitled2.jpg","usages":[]},{"id":"user-image-pexelsphoto2599039.jpeg","publicUrl":"np://user.desktop.nicepage.com/Site_1592210559/images/pexelsphoto2599039.jpeg","size":165720,"hash":"FUggfnNU2hd3H+rlEchM3HzWz68=","fileName":"pexelsphoto2599039.jpeg","name":"pexelsphoto2599039","width":1500,"height":1500,"thumbnail":{"url":"np://user.desktop.nicepage.com/Site_1592210559/images/thumbnails/pexelsphoto2599039.jpeg","width":250,"height":250},"folderId":null,"originalUrl":"//images03.nicepage.com/a1389d7bc73adea1e1c1fb7e/ddfd56b050cb5ca88bab1e2b/pexelsphoto2599039.jpeg","usages":[]},{"id":"user-image-DQWKX-fWAAAp6JL.jpg","publicUrl":"np://user.desktop.nicepage.com/Site_1592210559/images/DQWKX-fWAAAp6JL.jpg","size":240561,"hash":"kV7x2ILL6BLzhfICxjmieuz7xWE=","fileName":"DQWKX-fWAAAp6JL.jpg","name":"DQWKX-fWAAAp6JL","width":1200,"height":900,"thumbnail":{"url":"np://user.desktop.nicepage.com/Site_1592210559/images/thumbnails/DQWKX-fWAAAp6JL.jpg","width":250,"height":188},"folderId":null,"usages":[]},{"id":"user-image-646094.png","publicUrl":"np://user.desktop.nicepage.com/Site_1592210559/images/646094.png","size":2920,"hash":"D4R2eI+UniH8DFN5GIjVyvdbvvY=","fileName":"646094.png","name":"646094","width":128,"height":128,"thumbnail":{"url":"np://user.desktop.nicepage.com/Site_1592210559/images/thumbnails/646094.png","width":128,"height":128,"length":2920,"type":"png"},"folderId":null,"usages":[]},{"id":"user-image-pexels-ben-neale-380330.jpg","publicUrl":"np://user.desktop.nicepage.com/Site_1592210559/images/pexels-ben-neale-380330.jpg","size":75952,"hash":"UFBJhqP/HBRwiB6g6WiFWcMx3uI=","fileName":"pexels-ben-neale-380330.jpg","name":"pexels-ben-neale-380330","width":1280,"height":853,"thumbnail":{"url":"np://user.desktop.nicepage.com/Site_1592210559/images/thumbnails/pexels-ben-neale-380330.jpg","width":250,"height":167},"folderId":null,"originalUrl":"//images01.nicepagecdn.com/a1389d7bc73adea1e1c1fb7e/c32ba18df831592e97c14561/pexels-ben-neale-380330.jpg","usages":[]},{"id":"user-image-149239.png","publicUrl":"np://user.desktop.nicepage.com/Site_1592210559/images/149239.png","size":1930,"hash":"lxBR+GOZEfK9QCDpmgfzxAkKGn8=","fileName":"149239.png","name":"149239","width":128,"height":128,"thumbnail":{"url":"np://user.desktop.nicepage.com/Site_1592210559/images/thumbnails/149239.png","width":128,"height":128,"length":1930,"type":"png"},"folderId":null,"usages":[]},{"id":"user-image-1446-11-1103.21.04_4a108c26.jpg","publicUrl":"np://user.desktop.nicepage.com/Site_1592210559/images/1446-11-1103.21.04_4a108c26.jpg","size":27367,"hash":"bYOkEgmGiU+YV7hV0GwfEbKhd7s=","fileName":"1446-11-1103.21.04_4a108c26.jpg","name":"1446-11-1103.21.04_4a108c26","width":900,"height":271,"thumbnail":{"url":"np://user.desktop.nicepage.com/Site_1592210559/images/thumbnails/1446-11-1103.21.04_4a108c26.jpg","width":250,"height":75},"folderId":null,"usages":[]}]
